README.txt
setup.py
pyloader/__init__.py
pyloader/cast.py
pyloader/factory.py
pyloader/invoke.py
pyloader/loader.py
pyloader/parser.py
pyloader/require.py
pyloader.egg-info/PKG-INFO
pyloader.egg-info/SOURCES.txt
pyloader.egg-info/dependency_links.txt
pyloader.egg-info/entry_points.txt
pyloader.egg-info/not-zip-safe
pyloader.egg-info/top_level.txt