Metadata-Version: 1.0
Name: pyloader
Version: 0.1.3
Summary: Load python attributes from a string
Home-page: http://k0s.org/
Author: Jeff Hammel
Author-email: jhammel@mozilla.com
License: MPL
Platform: UNKNOWN
